nb_move_imports/__init__.py
nb_move_imports/main.py
nb_move_imports-0.4.5.dist-info/METADATA
nb_move_imports-0.4.5.dist-info/WHEEL
nb_move_imports-0.4.5.dist-info/entry_points.txt
nb_move_imports-0.4.5.dist-info/RECORD
