Metadata-Version: 2.1
Name: nb-move-imports
Version: 0.4.5
Summary: Move import statements in jupyter notebook to the first cell
Author: An Hoang
Author-email: anhoang31415@gmail.com
Requires-Python: >=3.8.9,<4.0.0
Classifier: Programming Language :: Python :: 3
Classifier: Programming Language :: Python :: 3.9
Classifier: Programming Language :: Python :: 3.10
Classifier: Programming Language :: Python :: 3.11
Provides-Extra: isort
Requires-Dist: click (>=8.1.3)
Requires-Dist: isort (>=5.10.1) ; extra == "isort"
Requires-Dist: nbformat (>=5.4.0)
